0 DEF_GLOBAL fibonacci
1 PUSH_LOCAL x
2 LOAD_FAST x
3 LOAD_CONST 0
4 COMPARE_OP ==
5 JUMP_IF_FALSE 9
6 LOAD_CONST 0
7 RETURN_VALUE
8 JUMP_ABSOLUTE 28
9 LOAD_FAST x
10 LOAD_CONST 1
11 COMPARE_OP ==
12 JUMP_IF_FALSE 16
13 LOAD_CONST 1
14 RETURN_VALUE
15 JUMP_ABSOLUTE 28
16 LOAD_FAST x
17 LOAD_CONST 1
18 BINARY_SUBSTRACT
19 LOAD_GLOBAL fibonacci
20 CALL_FUNCTION 1
21 LOAD_FAST x
22 LOAD_CONST 2
23 BINARY_SUBSTRACT
24 LOAD_GLOBAL fibonacci
25 CALL_FUNCTION 1
26 BINARY_ADD
27 RETURN_VALUE
28 RETURN
29 DEF_GLOBAL Main
30 PUSH_LOCAL main
31 PUSH_LOCAL result
32 LOAD_CONST 3
33 LOAD_GLOBAL fibonacci
34 CALL_FUNCTION 1
35 STORE_FAST result
36 LOAD_FAST result
37 LOAD_GLOBAL write
38 CALL_FUNCTION 1
39 RETURN
40 END
